SpringBootRumenjiaochengZhaiyongchao/README.md
SpringBootRumenjiaochengZhaiyongchao/__init__.py
SpringBootRumenjiaochengZhaiyongchao/__main__.py
SpringBootRumenjiaochengZhaiyongchao/file.epub
SpringBootRumenjiaochengZhaiyongchao/index.html
SpringBootRumenjiaochengZhaiyongchao/css/__init__.py
SpringBootRumenjiaochengZhaiyongchao/css/annotations.css
SpringBootRumenjiaochengZhaiyongchao/css/main.css
SpringBootRumenjiaochengZhaiyongchao/css/normalize.css
SpringBootRumenjiaochengZhaiyongchao/css/popup.css
SpringBootRumenjiaochengZhaiyongchao/font/__init__.py
SpringBootRumenjiaochengZhaiyongchao/font/fontello.eot
SpringBootRumenjiaochengZhaiyongchao/font/fontello.svg
SpringBootRumenjiaochengZhaiyongchao/font/fontello.ttf
SpringBootRumenjiaochengZhaiyongchao/font/fontello.woff
SpringBootRumenjiaochengZhaiyongchao/img/__init__.py
SpringBootRumenjiaochengZhaiyongchao/img/annotator-glyph-sprite.png
SpringBootRumenjiaochengZhaiyongchao/img/annotator-icon-sprite.png
SpringBootRumenjiaochengZhaiyongchao/img/apple-touch-icon.png
SpringBootRumenjiaochengZhaiyongchao/img/cancelfullscreen.png
SpringBootRumenjiaochengZhaiyongchao/img/close.png
SpringBootRumenjiaochengZhaiyongchao/img/fullscreen.png
SpringBootRumenjiaochengZhaiyongchao/img/loader.gif
SpringBootRumenjiaochengZhaiyongchao/img/menu-icon.png
SpringBootRumenjiaochengZhaiyongchao/img/save.png
SpringBootRumenjiaochengZhaiyongchao/img/saved.png
SpringBootRumenjiaochengZhaiyongchao/img/settings-s.png
SpringBootRumenjiaochengZhaiyongchao/img/settings.png
SpringBootRumenjiaochengZhaiyongchao/img/star.png
SpringBootRumenjiaochengZhaiyongchao/js/__init__.py
SpringBootRumenjiaochengZhaiyongchao/js/epub.js
SpringBootRumenjiaochengZhaiyongchao/js/epub.min.js
SpringBootRumenjiaochengZhaiyongchao/js/epub.min.map
SpringBootRumenjiaochengZhaiyongchao/js/hooks.min.js
SpringBootRumenjiaochengZhaiyongchao/js/hooks.min.map
SpringBootRumenjiaochengZhaiyongchao/js/reader.js
SpringBootRumenjiaochengZhaiyongchao/js/reader.js.map
spring_boot_rumenjiaocheng_zhaiyongchao-2024.3.2.0.dist-info/METADATA
spring_boot_rumenjiaocheng_zhaiyongchao-2024.3.2.0.dist-info/WHEEL
spring_boot_rumenjiaocheng_zhaiyongchao-2024.3.2.0.dist-info/entry_points.txt
spring_boot_rumenjiaocheng_zhaiyongchao-2024.3.2.0.dist-info/top_level.txt
spring_boot_rumenjiaocheng_zhaiyongchao-2024.3.2.0.dist-info/RECORD
